math_toolkit/__init__.py
math_toolkit/operations.py
math_toolkit-0.1.0.dist-info/LICENSE
math_toolkit-0.1.0.dist-info/METADATA
math_toolkit-0.1.0.dist-info/WHEEL
math_toolkit-0.1.0.dist-info/top_level.txt
math_toolkit-0.1.0.dist-info/RECORD
