Metadata-Version: 2.1
Name: math_toolkit
Version: 0.1.0
Summary: A simple math toolkit package
Home-page: https://github.com/prachikabra121/mathToolkit
Author: Prachi Kabra
Author-email: kabraprachi9@gmail.com
Classifier: Programming Language :: Python :: 3
Classifier: License :: OSI Approved :: MIT License
Classifier: Operating System :: OS Independent
Requires-Python: >=3.6
License-File: LICENSE
